contentcopy/__init__.py
contentcopy/contentcopy.py
contentcopy-1.1.0.dist-info/LICENSE
contentcopy-1.1.0.dist-info/METADATA
contentcopy-1.1.0.dist-info/WHEEL
contentcopy-1.1.0.dist-info/top_level.txt
contentcopy-1.1.0.dist-info/RECORD
