Metadata-Version: 2.1
Name: contentcopy
Version: 1.1.0
Summary: Merge directory contents, deduplicating files based on their content.
Home-page: https://github.com/KillianMeersman/contentcopy
Author: Killian Meersman
Author-email: hi@killianm.dev
License: UNKNOWN
Platform: UNKNOWN
Classifier: Programming Language :: Python :: 3
Classifier: License :: OSI Approved :: MIT License
Classifier: Operating System :: OS Independent
Requires-Python: >=3.6
